iec62056/__init__.py
iec62056/grammar.lark
iec62056/objects.py
iec62056/parser.py
iec62056/samples.py
iec62056-0.5.1.dist-info/LICENSE
iec62056-0.5.1.dist-info/METADATA
iec62056-0.5.1.dist-info/WHEEL
iec62056-0.5.1.dist-info/top_level.txt
iec62056-0.5.1.dist-info/RECORD
