Metadata-Version: 2.1
Name: iec62056
Version: 0.5.1
Summary: Library to parse IEC62056/IEC1107/DSMR telegrams
Home-page: https://github.com/jonkerj/iec62056
Author: Jorik Jonker
Author-email: jorik@kippendief.biz
License: GPLv3
Project-URL: Documentation, https://github.com/jonkerj/iec62056
Project-URL: Source, https://github.com/jonkerj/iec62056
Project-URL: Tracker, https://github.com/jonkerj/iec62056
Classifier: Development Status :: 3 - Alpha
Classifier: Intended Audience :: Developers
Classifier: License :: OSI Approved :: GNU General Public License v3 (GPLv3)
Classifier: Natural Language :: English
Classifier: Operating System :: OS Independent
Classifier: Programming Language :: Python :: 3
Classifier: Programming Language :: Python
Classifier: Topic :: Software Development :: Libraries :: Python Modules
Classifier: Topic :: Software Development :: Libraries
License-File: LICENSE
Requires-Dist: lark (==1.0.0)
